Divisor/Verilog/Control_div.v
// Module: div_fsm
module Control_div #(parameter N = 16)(
    input  wire clk,
    input  wire rst,
    input  wire start,
    input  wire N_in,      
    output reg  LD,       
    output reg  SHFT,      
    output reg  SUB,       
    output reg  Q0,       
    output reg  Q1,       
    output reg  DONE
);

    localparam [2:0]
        S_START  = 3'd0,
        S_LOAD  = 3'd1,
        S_WAIT  = 3'd2,
        S_SHIFT = 3'd3,
        S_CHECK = 3'd4,
        S_DONE  = 3'd5;

    localparam CNT_W = 5;         

    reg [2:0]      state;
    reg [CNT_W-1:0] cnt;

// Valores iniciales

    initial begin
        LD    = 0;
        SHFT  = 0;
        SUB   = 0;
        Q0    = 0;
        Q1    = 0;
        DONE  = 0;
        state = S_START;
        cnt   = 0;
    end


    always @(posedge clk) begin
        if (rst) begin
            state <= S_START;
        end
        else begin
            case (state)

                S_START: begin
                    LD   <= 0;
                    SHFT <= 0;
                    SUB  <= 0;
                    Q0   <= 0;
                    Q1   <= 0;
                    DONE <= 0;
                    cnt  <= 0;
                    if (start)
                        state <= S_LOAD;
                    else
                        state <= S_START;
                end

                S_LOAD: begin
                    LD   <= 1;
                    SHFT <= 0;
                    SUB  <= 0;
                    Q0   <= 0;
                    Q1   <= 0;
                    DONE <= 0;
                    state <= S_WAIT;
                end

                S_WAIT: begin
                    LD   <= 0;
                    SHFT <= 0;
                    SUB  <= 0;
                    Q0   <= 0;
                    Q1   <= 0;
                    DONE <= 0;
                    state <= S_SHIFT;
                end

                S_SHIFT: begin
                    LD   <= 0;
                    SHFT <= 1;
                    SUB  <= 0;
                    Q0   <= 0;
                    Q1   <= 0;
                    DONE <= 0;
                    state <= S_CHECK;
                end

                S_CHECK: begin
                    LD   <= 0;
                    SHFT <= 0;
                    DONE <= 0;
                    if (N_in) begin
                        // Acm >= Dvs: resta y mete 1 al cociente
                        SUB <= 1;
                        Q1  <= 1;
                        Q0  <= 0;
                    end
                    else begin
                        // Acm < Dvs: No resta y mete 0 al cociente
                        SUB <= 0;
                        Q1  <= 0;
                        Q0  <= 1;
                    end

                    if (cnt == N-1) begin
                        state <= S_DONE;
                    end
                    else begin
                        state <= S_SHIFT;
                        cnt   <= cnt + 1'b1;
                    end
                end

                S_DONE: begin
                    LD    <= 0;
                    SHFT  <= 0;
                    SUB   <= 0;
                    Q0    <= 0;
                    Q1    <= 0;
                    DONE  <= 1;
                    state <= S_START;
                end

                default: state <= S_START;

            endcase
        end
    end

`ifdef BENCH
    reg [8*40:1] state_name;
    always @(*) begin
        case (state)
            S_START  : state_name = "START";
            S_LOAD  : state_name = "LOAD";
            S_WAIT  : state_name = "WAIT";
            S_SHIFT : state_name = "SHIFT";
            S_CHECK : state_name = "CHECK";
            S_DONE  : state_name = "DONE";
        endcase
    end
`endif

endmodule

Divisor/Verilog/div_comp.v
module div_comp #(
    parameter N = 16
)(
    input  wire [N-1:0] Dvd, Dvs,
    output wire         Z,
    output wire         N_out
);
    assign Z     = (Dvd == Dvs);
    assign N_out = (Dvd >= Dvs);
endmodule

Divisor/Verilog/reg_c.v
//   LD  → clear a 0
//   Q0  → entra 0 (Acm < Dvs)
//   Q1  → entra 1 (Acm >= Dvs)

module reg_c #(
    parameter N = 16
)(
    input  wire         clk, rst,
    input  wire         LD, Q0, Q1,
    output reg  [N-1:0] Q
);
    always @(negedge clk or posedge rst) begin
        if (rst)     Q <= {N{1'b0}};
        else if (LD) Q <= {N{1'b0}};
        else if (Q1) Q <= {Q[N-2:0], 1'b1};
        else if (Q0) Q <= {Q[N-2:0], 1'b0};
    end
endmodule

Divisor/Verilog/acm_reg.v
module acm_reg #(
    parameter N = 16
)(
    input  wire         clk, rst,
    input  wire         LD,
    input  wire         SHFT,
    input  wire         SUB,
    input  wire         Dvd_MSB,
    input  wire [N-1:0] Dvs,
    output reg  [N-1:0] Q
);
    always @(negedge clk or posedge rst) begin
        if (rst)       Q <= {N{1'b0}};
        else if (LD)   Q <= {N{1'b0}};
        else if (SHFT) Q <= {Q[N-2:0], Dvd_MSB};
        else if (SUB)  Q <= Q - Dvs;
    end
endmodule

Divisor/Verilog/div_sh_reg.v
//   DIR=1 → left shift
//   DIR=0 → right shift
//   LD    → carga paralela desde D
//   SHFT  → desplaza un bit

module div_sh_reg #(
    parameter N   = 16,
    parameter DIR = 1
)(
    input  wire         clk, rst,
    input  wire         LD, SHFT,
    input  wire [N-1:0] D,
    output reg  [N-1:0] Q,
    output wire         MSB,
    output wire         LSB
);
    assign MSB = Q[N-1];
    assign LSB = Q[0];

    always @(negedge clk or posedge rst) begin
        if (rst)       Q <= {N{1'b0}};
        else if (LD)   Q <= D;
        else if (SHFT) Q <= (DIR==1) ? {Q[N-2:0], 1'b0} : {1'b0, Q[N-1:1]};
    end
endmodule

Divisor/Verilog/top_div.v
module top_div #(parameter N = 16)(
    input  wire         clk, rst, start,
    input  wire [N-1:0] Dvd_in,
    input  wire [N-1:0] Dvs_in,
    output wire [N-1:0] Q_out,
    output wire [N-1:0] R_out,
    output wire         done
);
 
    wire LD, SHFT, SUB, Q0, Q1;


    wire [N-1:0] Dvd_q;       
    wire [N-1:0] Acm_q;       
    wire [N-1:0] Dvs_q;       
    wire [N-1:0] C_q;         
    wire         Dvd_MSB;     
    wire         Acm_geq_Dvs; 
    // ---- dividendo----
    div_sh_reg #(.N(N), .DIR(1)) Dvd_REG (
        .clk(clk), .rst(rst),
        .LD(LD), .SHFT(SHFT),
        .D(Dvd_in),
        .Q(Dvd_q),
        .MSB(Dvd_MSB), .LSB()
    );

    // ---- divisor ----
    div_sh_reg #(.N(N), .DIR(1)) Dvs_REG (
        .clk(clk), .rst(rst),
        .LD(LD), .SHFT(1'b0),
        .D(Dvs_in),
        .Q(Dvs_q),
        .MSB(), .LSB()
    );

    // ---- acumulador ----
    acm_reg #(.N(N)) Acm_REG (
        .clk(clk), .rst(rst),
        .LD(LD),
        .SHFT(SHFT),
        .SUB(SUB),
        .Dvd_MSB(Dvd_MSB),
        .Dvs(Dvs_q),
        .Q(Acm_q)
    );

    // ---- cociente ----
    reg_c #(.N(N)) C_REG (
        .clk(clk), .rst(rst),
        .LD(LD),
        .Q0(Q0),
        .Q1(Q1),
        .Q(C_q)
    );

    // ---- Comparador ----
    div_comp #(.N(N)) COMP (
        .Dvd(Acm_q), .Dvs(Dvs_q),
        .Z(), .N_out(Acm_geq_Dvs)
    );

    // ---- FSM ----
    Control_div #(.N(N)) FSM (
        .clk(clk), .rst(rst), .start(start),
        .N_in(Acm_geq_Dvs),
        .LD(LD), .SHFT(SHFT), .SUB(SUB), .Q0(Q0), .Q1(Q1),
        .DONE(done)
    );

    assign Q_out = C_q;
    assign R_out = Acm_q;
endmodule

Divisor/Verilog/tb_div.v
`timescale 1ns/1ps
// `include "top_div.v"
// `include "div_sh_reg.v"
// `include "div_comp.v"
// `include "Control_div.v"
// `include "acm_reg.v"
// `include "reg_c.v"

module tb_div;

parameter N = 16;

reg clk;
reg rst;
reg start;

reg [N-1:0] Dvd_in;
reg [N-1:0] Dvs_in;

wire [N-1:0] Q_out;
wire [N-1:0] R_out;
wire done;

top_div #(N) UUT (
    .clk(clk), 
    .rst(rst),
    .start(start),
    .Dvd_in(Dvd_in),
    .Dvs_in(Dvs_in),
    .Q_out(Q_out),
    .R_out(R_out),
    .done(done)
);

always #5 clk = ~clk;

initial begin

    $dumpfile("div.vcd");
    $dumpvars(0, tb_div);

    clk    = 0;
    rst    = 1;
    start  = 0;
    Dvd_in = 0;
    Dvs_in = 1;

// Reset
    #20;
    rst = 0;

// Caso 1 : 29 / 4
// ==========================
    #10;
    Dvd_in = 16'd29;
    Dvs_in = 16'd4;

    start = 1;
    #10;
    start = 0;

    wait(done);

    $display("---------------------");
    $display("29 / 4");
    $display("Q = %0d", Q_out);
    $display("R = %0d", R_out);

// reset
    #20;
    rst = 1;
    #10;
    rst = 0;

    
// Caso 2 : 318 / 3
// ==========================
    #10;
    Dvd_in = 16'd318;
    Dvs_in = 16'd3;

    start = 1;
    #10;
    start = 0;

    wait(done);

    $display("---------------------");
    $display("318 / 3");
    $display("Q = %0d", Q_out);
    $display("R = %0d", R_out);

    #20;
    rst = 1;
    #10;
    rst = 0;

// Caso 3 : 520 / 6
// ==========================
    #10;
    Dvd_in = 16'd520;
    Dvs_in = 16'd6;

    start = 1;
    #10;
    start = 0;

    wait(done);

    $display("---------------------");
    $display("520 / 6");
    $display("Q = %0d", Q_out);
    $display("R = %0d", R_out);

    #30;
    $finish;

end

endmodule

Divisor/Verilog/div.vcd
$date
	Thu Jul 16 16:44:29 2026
$end
$version
	Icarus Verilog
$end
$timescale
	1ps
$end
$scope module tb_div $end
$var wire 1 ! done $end
$var wire 16 " R_out [15:0] $end
$var wire 16 # Q_out [15:0] $end
$var parameter 32 $ N $end
$var reg 16 % Dvd_in [15:0] $end
$var reg 16 & Dvs_in [15:0] $end
$var reg 1 ' clk $end
$var reg 1 ( rst $end
$var reg 1 ) start $end
$scope module UUT $end
$var wire 16 * Dvd_in [15:0] $end
$var wire 16 + Dvs_in [15:0] $end
$var wire 16 , Q_out [15:0] $end
$var wire 16 - R_out [15:0] $end
$var wire 1 ' clk $end
$var wire 1 ( rst $end
$var wire 1 ) start $end
$var wire 1 ! done $end
$var wire 1 . SUB $end
$var wire 1 / SHFT $end
$var wire 1 0 Q1 $end
$var wire 1 1 Q0 $end
$var wire 1 2 LD $end
$var wire 16 3 Dvs_q [15:0] $end
$var wire 16 4 Dvd_q [15:0] $end
$var wire 1 5 Dvd_MSB $end
$var wire 16 6 C_q [15:0] $end
$var wire 16 7 Acm_q [15:0] $end
$var wire 1 8 Acm_geq_Dvs $end
$var parameter 32 9 N $end
$scope module Acm_REG $end
$var wire 1 ' clk $end
$var wire 1 ( rst $end
$var wire 1 . SUB $end
$var wire 1 / SHFT $end
$var wire 1 2 LD $end
$var wire 16 : Dvs [15:0] $end
$var wire 1 5 Dvd_MSB $end
$var parameter 32 ; N $end
$var reg 16 < Q [15:0] $end
$upscope $end
$scope module COMP $end
$var wire 16 = Dvd [15:0] $end
$var wire 1 > Z $end
$var wire 1 8 N_out $end
$var wire 16 ? Dvs [15:0] $end
$var parameter 32 @ N $end
$upscope $end
$scope module C_REG $end
$var wire 1 ' clk $end
$var wire 1 ( rst $end
$var wire 1 0 Q1 $end
$var wire 1 1 Q0 $end
$var wire 1 2 LD $end
$var parameter 32 A N $end
$var reg 16 B Q [15:0] $end
$upscope $end
$scope module Dvd_REG $end
$var wire 16 C D [15:0] $end
$var wire 1 ' clk $end
$var wire 1 ( rst $end
$var wire 1 / SHFT $end
$var wire 1 5 MSB $end
$var wire 1 D LSB $end
$var wire 1 2 LD $end
$var parameter 32 E DIR $end
$var parameter 32 F N $end
$var reg 16 G Q [15:0] $end
$upscope $end
$scope module Dvs_REG $end
$var wire 16 H D [15:0] $end
$var wire 1 I SHFT $end
$var wire 1 ' clk $end
$var wire 1 ( rst $end
$var wire 1 J MSB $end
$var wire 1 K LSB $end
$var wire 1 2 LD $end
$var parameter 32 L DIR $end
$var parameter 32 M N $end
$var reg 16 N Q [15:0] $end
$upscope $end
$scope module FSM $end
$var wire 1 8 N_in $end
$var wire 1 ' clk $end
$var wire 1 ( rst $end
$var wire 1 ) start $end
$var parameter 32 O CNT_W $end
$var parameter 32 P N $end
$var parameter 3 Q S_CHECK $end
$var parameter 3 R S_DONE $end
$var parameter 3 S S_LOAD $end
$var parameter 3 T S_SHIFT $end
$var parameter 3 U S_START $end
$var parameter 3 V S_WAIT $end
$var reg 1 ! DONE $end
$var reg 1 2 LD $end
$var reg 1 1 Q0 $end
$var reg 1 0 Q1 $end
$var reg 1 / SHFT $end
$var reg 1 . SUB $end
$var reg 5 W cnt [4:0] $end
$var reg 3 X state [2:0] $end
$var reg 320 Y state_name [320:1] $end
$upscope $end
$upscope $end
$upscope $end
$enddefinitions $end
$comment Show the parameter values. $end
$dumpall
b10 V
b0 U
b11 T
b1 S
b101 R
b100 Q
b10000 P
b101 O
b10000 M
b1 L
b10000 F
b1 E
b10000 A
b10000 @
b10000 ;
b10000 9
b10000 $
$end
#0
$dumpvars
b101001101010100010000010101001001010100 Y
b0 X
b0 W
b0 N
0K
0J
0I
b1 H
b0 G
0D
b0 C
b0 B
b0 ?
1>
b0 =
b0 <
b0 :
18
b0 7
b0 6
05
b0 4
b0 3
02
01
00
0/
0.
b0 -
b0 ,
b1 +
b0 *
0)
1(
0'
b1 &
b0 %
b0 #
b0 "
0!
$end
#5000
1'
#10000
0'
#15000
1'
#20000
0'
0(
#25000
1'
#30000
0'
1)
b100 &
b100 +
b100 H
b11101 %
b11101 *
b11101 C
#35000
b1001100010011110100000101000100 Y
b1 X
1'
#40000
0'
0)
#45000
b1010111010000010100100101010100 Y
b10 X
12
1'
#50000
1D
08
0>
b100 3
b100 :
b100 ?
b100 N
b11101 4
b11101 G
0'
#55000
b101001101001000010010010100011001010100 Y
b11 X
02
1'
#60000
0'
#65000
b100001101001000010001010100001101001011 Y
b100 X
1/
1'
#70000
0D
b111010 4
b111010 G
0'
#75000
b101001101001000010010010100011001010100 Y
b1 W
b11 X
11
0/
1'
#80000
0'
#85000
b100001101001000010001010100001101001011 Y
b100 X
01
1/
1'
#90000
b1110100 4
b1110100 G
0'
#95000
b101001101001000010010010100011001010100 Y
b10 W
b11 X
11
0/
1'
#100000
0'
#105000
b100001101001000010001010100001101001011 Y
b100 X
01
1/
1'
#110000
b11101000 4
b11101000 G
0'
#115000
b101001101001000010010010100011001010100 Y
b11 W
b11 X
11
0/
1'
#120000
0'
#125000
b100001101001000010001010100001101001011 Y
b100 X
01
1/
1'
#130000
b111010000 4
b111010000 G
0'
#135000
b101001101001000010010010100011001010100 Y
b100 W
b11 X
11
0/
1'
#140000
0'
#145000
b100001101001000010001010100001101001011 Y
b100 X
01
1/
1'
#150000
b1110100000 4
b1110100000 G
0'
#155000
b101001101001000010010010100011001010100 Y
b101 W
b11 X
11
0/
1'
#160000
0'
#165000
b100001101001000010001010100001101001011 Y
b100 X
01
1/
1'
#170000
b11101000000 4
b11101000000 G
0'
#175000
b101001101001000010010010100011001010100 Y
b110 W
b11 X
11
0/
1'
#180000
0'
#185000
b100001101001000010001010100001101001011 Y
b100 X
01
1/
1'
#190000
b111010000000 4
b111010000000 G
0'
#195000
b101001101001000010010010100011001010100 Y
b111 W
b11 X
11
0/
1'
#200000
0'
#205000
b100001101001000010001010100001101001011 Y
b100 X
01
1/
1'
#210000
b1110100000000 4
b1110100000000 G
0'
#215000
b101001101001000010010010100011001010100 Y
b1000 W
b11 X
11
0/
1'
#220000
0'
#225000
b100001101001000010001010100001101001011 Y
b100 X
01
1/
1'
#230000
b11101000000000 4
b11101000000000 G
0'
#235000
b101001101001000010010010100011001010100 Y
b1001 W
b11 X
11
0/
1'
#240000
0'
#245000
b100001101001000010001010100001101001011 Y
b100 X
01
1/
1'
#250000
b111010000000000 4
b111010000000000 G
0'
#255000
b101001101001000010010010100011001010100 Y
b1010 W
b11 X
11
0/
1'
#260000
0'
#265000
b100001101001000010001010100001101001011 Y
b100 X
01
1/
1'
#270000
15
b1110100000000000 4
b1110100000000000 G
0'
#275000
b101001101001000010010010100011001010100 Y
b1011 W
b11 X
11
0/
1'
#280000
0'
#285000
b100001101001000010001010100001101001011 Y
b100 X
01
1/
1'
#290000
b1 "
b1 -
b1 7
b1 <
b1 =
b1101000000000000 4
b1101000000000000 G
0'
#295000
b101001101001000010010010100011001010100 Y
b1100 W
b11 X
11
0/
1'
#300000
0'
#305000
b100001101001000010001010100001101001011 Y
b100 X
01
1/
1'
#310000
b11 "
b11 -
b11 7
b11 <
b11 =
b1010000000000000 4
b1010000000000000 G
0'
#315000
b101001101001000010010010100011001010100 Y
b1101 W
b11 X
11
0/
1'
#320000
0'
#325000
b100001101001000010001010100001101001011 Y
b100 X
01
1/
1'
#330000
05
18
b111 "
b111 -
b111 7
b111 <
b111 =
b100000000000000 4
b100000000000000 G
0'
#335000
b101001101001000010010010100011001010100 Y
b1110 W
b11 X
10
1.
0/
1'
#340000
08
b11 "
b11 -
b11 7
b11 <
b11 =
b1 #
b1 ,
b1 6
b1 B
0'
#345000
b100001101001000010001010100001101001011 Y
b100 X
00
0.
1/
1'
#350000
15
18
b110 "
b110 -
b110 7
b110 <
b110 =
b1000000000000000 4
b1000000000000000 G
0'
#355000
b101001101001000010010010100011001010100 Y
b1111 W
b11 X
10
1.
0/
1'
#360000
08
b10 "
b10 -
b10 7
b10 <
b10 =
b11 #
b11 ,
b11 6
b11 B
0'
#365000
b100001101001000010001010100001101001011 Y
b100 X
00
0.
1/
1'
#370000
05
18
b101 "
b101 -
b101 7
b101 <
b101 =
b0 4
b0 G
0'
#375000
b1000100010011110100111001000101 Y
b101 X
10
1.
0/
1'
#380000
08
b1 "
b1 -
b1 7
b1 <
b1 =
b111 #
b111 ,
b111 6
b111 B
0'
#385000
b101001101010100010000010101001001010100 Y
b0 X
1!
00
0.
1'
#390000
0'
#395000
b0 W
0!
1'
#400000
0'
#405000
b0 #
b0 ,
b0 6
b0 B
1>
b0 "
b0 -
b0 7
b0 <
b0 =
18
b0 3
b0 :
b0 ?
b0 N
1'
1(
#410000
0'
#415000
1'
0(
#420000
0'
#425000
b1001100010011110100000101000100 Y
b1 X
1'
1)
b11 &
b11 +
b11 H
b100111110 %
b100111110 *
b100111110 C
#430000
0'
#435000
b1010111010000010100100101010100 Y
b10 X
12
1'
0)
#440000
1K
08
0>
b11 3
b11 :
b11 ?
b11 N
b100111110 4
b100111110 G
0'
#445000
b101001101001000010010010100011001010100 Y
b11 X
02
1'
#450000
0'
#455000
b100001101001000010001010100001101001011 Y
b100 X
1/
1'
#460000
b1001111100 4
b1001111100 G
0'
#465000
b101001101001000010010010100011001010100 Y
b1 W
b11 X
11
0/
1'
#470000
0'
#475000
b100001101001000010001010100001101001011 Y
b100 X
01
1/
1'
#480000
b10011111000 4
b10011111000 G
0'
#485000
b101001101001000010010010100011001010100 Y
b10 W
b11 X
11
0/
1'
#490000
0'
#495000
b100001101001000010001010100001101001011 Y
b100 X
01
1/
1'
#500000
b100111110000 4
b100111110000 G
0'
#505000
b101001101001000010010010100011001010100 Y
b11 W
b11 X
11
0/
1'
#510000
0'
#515000
b100001101001000010001010100001101001011 Y
b100 X
01
1/
1'
#520000
b1001111100000 4
b1001111100000 G
0'
#525000
b101001101001000010010010100011001010100 Y
b100 W
b11 X
11
0/
1'
#530000
0'
#535000
b100001101001000010001010100001101001011 Y
b100 X
01
1/
1'
#540000
b10011111000000 4
b10011111000000 G
0'
#545000
b101001101001000010010010100011001010100 Y
b101 W
b11 X
11
0/
1'
#550000
0'
#555000
b100001101001000010001010100001101001011 Y
b100 X
01
1/
1'
#560000
b100111110000000 4
b100111110000000 G
0'
#565000
b101001101001000010010010100011001010100 Y
b110 W
b11 X
11
0/
1'
#570000
0'
#575000
b100001101001000010001010100001101001011 Y
b100 X
01
1/
1'
#580000
15
b1001111100000000 4
b1001111100000000 G
0'
#585000
b101001101001000010010010100011001010100 Y
b111 W
b11 X
11
0/
1'
#590000
0'
#595000
b100001101001000010001010100001101001011 Y
b100 X
01
1/
1'
#600000
05
b1 "
b1 -
b1 7
b1 <
b1 =
b11111000000000 4
b11111000000000 G
0'
#605000
b101001101001000010010010100011001010100 Y
b1000 W
b11 X
11
0/
1'
#610000
0'
#615000
b100001101001000010001010100001101001011 Y
b100 X
01
1/
1'
#620000
b10 "
b10 -
b10 7
b10 <
b10 =
b111110000000000 4
b111110000000000 G
0'
#625000
b101001101001000010010010100011001010100 Y
b1001 W
b11 X
11
0/
1'
#630000
0'
#635000
b100001101001000010001010100001101001011 Y
b100 X
01
1/
1'
#640000
15
18
b100 "
b100 -
b100 7
b100 <
b100 =
b1111100000000000 4
b1111100000000000 G
0'
#645000
b101001101001000010010010100011001010100 Y
b1010 W
b11 X
10
1.
0/
1'
#650000
08
b1 "
b1 -
b1 7
b1 <
b1 =
b1 #
b1 ,
b1 6
b1 B
0'
#655000
b100001101001000010001010100001101001011 Y
b100 X
00
0.
1/
1'
#660000
1>
18
b11 "
b11 -
b11 7
b11 <
b11 =
b1111000000000000 4
b1111000000000000 G
0'
#665000
b101001101001000010010010100011001010100 Y
b1011 W
b11 X
10
1.
0/
1'
#670000
0>
08
b0 "
b0 -
b0 7
b0 <
b0 =
b11 #
b11 ,
b11 6
b11 B
0'
#675000
b100001101001000010001010100001101001011 Y
b100 X
00
0.
1/
1'
#680000
b1 "
b1 -
b1 7
b1 <
b1 =
b1110000000000000 4
b1110000000000000 G
0'
#685000
b101001101001000010010010100011001010100 Y
b1100 W
b11 X
11
0/
1'
#690000
b110 #
b110 ,
b110 6
b110 B
0'
#695000
b100001101001000010001010100001101001011 Y
b100 X
01
1/
1'
#700000
1>
18
b11 "
b11 -
b11 7
b11 <
b11 =
b1100000000000000 4
b1100000000000000 G
0'
#705000
b101001101001000010010010100011001010100 Y
b1101 W
b11 X
10
1.
0/
1'
#710000
0>
08
b0 "
b0 -
b0 7
b0 <
b0 =
b1101 #
b1101 ,
b1101 6
b1101 B
0'
#715000
b100001101001000010001010100001101001011 Y
b100 X
00
0.
1/
1'
#720000
b1 "
b1 -
b1 7
b1 <
b1 =
b1000000000000000 4
b1000000000000000 G
0'
#725000
b101001101001000010010010100011001010100 Y
b1110 W
b11 X
11
0/
1'
#730000
b11010 #
b11010 ,
b11010 6
b11010 B
0'
#735000
b100001101001000010001010100001101001011 Y
b100 X
01
1/
1'
#740000
05
1>
18
b11 "
b11 -
b11 7
b11 <
b11 =
b0 4
b0 G
0'
#745000
b101001101001000010010010100011001010100 Y
b1111 W
b11 X
10
1.
0/
1'
#750000
0>
08
b0 "
b0 -
b0 7
b0 <
b0 =
b110101 #
b110101 ,
b110101 6
b110101 B
0'
#755000
b100001101001000010001010100001101001011 Y
b100 X
00
0.
1/
1'
#760000
0'
#765000
b1000100010011110100111001000101 Y
b101 X
11
0/
1'
#770000
b1101010 #
b1101010 ,
b1101010 6
b1101010 B
0'
#775000
b101001101010100010000010101001001010100 Y
b0 X
1!
01
1'
#780000
0'
#785000
b0 W
0!
1'
#790000
0'
#795000
0K
b0 #
b0 ,
b0 6
b0 B
18
1>
b0 3
b0 :
b0 ?
b0 N
1'
1(
#800000
0'
#805000
1'
0(
#810000
0'
#815000
b1001100010011110100000101000100 Y
b1 X
1'
1)
b110 &
b110 +
b110 H
b1000001000 %
b1000001000 *
b1000001000 C
#820000
0'
#825000
b1010111010000010100100101010100 Y
b10 X
12
1'
0)
#830000
08
0>
b110 3
b110 :
b110 ?
b110 N
b1000001000 4
b1000001000 G
0'
#835000
b101001101001000010010010100011001010100 Y
b11 X
02
1'
#840000
0'
#845000
b100001101001000010001010100001101001011 Y
b100 X
1/
1'
#850000
b10000010000 4
b10000010000 G
0'
#855000
b101001101001000010010010100011001010100 Y
b1 W
b11 X
11
0/
1'
#860000
0'
#865000
b100001101001000010001010100001101001011 Y
b100 X
01
1/
1'
#870000
b100000100000 4
b100000100000 G
0'
#875000
b101001101001000010010010100011001010100 Y
b10 W
b11 X
11
0/
1'
#880000
0'
#885000
b100001101001000010001010100001101001011 Y
b100 X
01
1/
1'
#890000
b1000001000000 4
b1000001000000 G
0'
#895000
b101001101001000010010010100011001010100 Y
b11 W
b11 X
11
0/
1'
#900000
0'
#905000
b100001101001000010001010100001101001011 Y
b100 X
01
1/
1'
#910000
b10000010000000 4
b10000010000000 G
0'
#915000
b101001101001000010010010100011001010100 Y
b100 W
b11 X
11
0/
1'
#920000
0'
#925000
b100001101001000010001010100001101001011 Y
b100 X
01
1/
1'
#930000
b100000100000000 4
b100000100000000 G
0'
#935000
b101001101001000010010010100011001010100 Y
b101 W
b11 X
11
0/
1'
#940000
0'
#945000
b100001101001000010001010100001101001011 Y
b100 X
01
1/
1'
#950000
15
b1000001000000000 4
b1000001000000000 G
0'
#955000
b101001101001000010010010100011001010100 Y
b110 W
b11 X
11
0/
1'
#960000
0'
#965000
b100001101001000010001010100001101001011 Y
b100 X
01
1/
1'
#970000
05
b1 "
b1 -
b1 7
b1 <
b1 =
b10000000000 4
b10000000000 G
0'
#975000
b101001101001000010010010100011001010100 Y
b111 W
b11 X
11
0/
1'
#980000
0'
#985000
b100001101001000010001010100001101001011 Y
b100 X
01
1/
1'
#990000
b10 "
b10 -
b10 7
b10 <
b10 =
b100000000000 4
b100000000000 G
0'
#995000
b101001101001000010010010100011001010100 Y
b1000 W
b11 X
11
0/
1'
#1000000
0'
#1005000
b100001101001000010001010100001101001011 Y
b100 X
01
1/
1'
#1010000
b100 "
b100 -
b100 7
b100 <
b100 =
b1000000000000 4
b1000000000000 G
0'
#1015000
b101001101001000010010010100011001010100 Y
b1001 W
b11 X
11
0/
1'
#1020000
0'
#1025000
b100001101001000010001010100001101001011 Y
b100 X
01
1/
1'
#1030000
18
b1000 "
b1000 -
b1000 7
b1000 <
b1000 =
b10000000000000 4
b10000000000000 G
0'
#1035000
b101001101001000010010010100011001010100 Y
b1010 W
b11 X
10
1.
0/
1'
#1040000
08
b10 "
b10 -
b10 7
b10 <
b10 =
b1 #
b1 ,
b1 6
b1 B
0'
#1045000
b100001101001000010001010100001101001011 Y
b100 X
00
0.
1/
1'
#1050000
b100 "
b100 -
b100 7
b100 <
b100 =
b100000000000000 4
b100000000000000 G
0'
#1055000
b101001101001000010010010100011001010100 Y
b1011 W
b11 X
11
0/
1'
#1060000
b10 #
b10 ,
b10 6
b10 B
0'
#1065000
b100001101001000010001010100001101001011 Y
b100 X
01
1/
1'
#1070000
15
18
b1000 "
b1000 -
b1000 7
b1000 <
b1000 =
b1000000000000000 4
b1000000000000000 G
0'
#1075000
b101001101001000010010010100011001010100 Y
b1100 W
b11 X
10
1.
0/
1'
#1080000
08
b10 "
b10 -
b10 7
b10 <
b10 =
b101 #
b101 ,
b101 6
b101 B
0'
#1085000
b100001101001000010001010100001101001011 Y
b100 X
00
0.
1/
1'
#1090000
05
b101 "
b101 -
b101 7
b101 <
b101 =
b0 4
b0 G
0'
#1095000
b101001101001000010010010100011001010100 Y
b1101 W
b11 X
11
0/
1'
#1100000
b1010 #
b1010 ,
b1010 6
b1010 B
0'
#1105000
b100001101001000010001010100001101001011 Y
b100 X
01
1/
1'
#1110000
18
b1010 "
b1010 -
b1010 7
b1010 <
b1010 =
0'
#1115000
b101001101001000010010010100011001010100 Y
b1110 W
b11 X
10
1.
0/
1'
#1120000
08
b100 "
b100 -
b100 7
b100 <
b100 =
b10101 #
b10101 ,
b10101 6
b10101 B
0'
#1125000
b100001101001000010001010100001101001011 Y
b100 X
00
0.
1/
1'
#1130000
18
b1000 "
b1000 -
b1000 7
b1000 <
b1000 =
0'
#1135000
b101001101001000010010010100011001010100 Y
b1111 W
b11 X
10
1.
0/
1'
#1140000
08
b10 "
b10 -
b10 7
b10 <
b10 =
b101011 #
b101011 ,
b101011 6
b101011 B
0'
#1145000
b100001101001000010001010100001101001011 Y
b100 X
00
0.
1/
1'
#1150000
b100 "
b100 -
b100 7
b100 <
b100 =
0'
#1155000
b1000100010011110100111001000101 Y
b101 X
11
0/
1'
#1160000
b1010110 #
b1010110 ,
b1010110 6
b1010110 B
0'
#1165000
b101001101010100010000010101001001010100 Y
b0 X
1!
01
1'
#1170000
0'
#1175000
b0 W
0!
1'
