Multiplicador/Verilog/control_unit.v

module control_unit(
    input  wire clk,
    input  wire rst,
    input  wire start,    
    input  wire Y_LSB,   
    input  wire Y_ZERO,   
    output reg  LD,       
    output reg  SHIFT,    
    output reg  ADD,
    output reg  DONE      
);

    localparam [2:0]
        S_START = 3'd0,
        S_CHECK = 3'd1,
        S_ADD   = 3'd2,
        S_SHIFT = 3'd3,
        S_END   = 3'd4;

    localparam [4:0] HOLD_CYCLES = 5'd28;

    reg [2:0] state;
    reg [4:0] count;


    initial begin
        DONE  = 0;
        SHIFT = 0;
        LD    = 0;
        ADD   = 0;
        state = S_START;
        count = 0;
    end


    always @(posedge clk) begin
        if (rst) begin
            state <= S_START;
        end
        else begin
            case (state)

                S_START: begin
                    DONE  <= 0;
                    SHIFT <= 0;
                    LD    <= 1;   // reset/carga del datapath
                    ADD   <= 0;
                    count <= 5'd0;
                    if (start)
                        state <= S_CHECK;
                    else
                        state <= S_START;
                end

                S_CHECK: begin
                    DONE  <= 0;
                    SHIFT <= 0;
                    LD    <= 0;
                    ADD   <= 0;
                    if (Y_LSB)
                        state <= S_ADD;
                    else
                        state <= S_SHIFT;
                end

                S_ADD: begin
                    DONE  <= 0;
                    SHIFT <= 0;
                    LD    <= 0;
                    ADD   <= 1;
                    state <= S_SHIFT;
                end

                S_SHIFT: begin
                    DONE  <= 0;
                    SHIFT <= 1;
                    LD    <= 0;
                    ADD   <= 0;
                    if (Y_ZERO)
                        state <= S_END;
                    else
                        state <= S_CHECK;
                end

                S_END: begin
                    DONE  <= 1;
                    SHIFT <= 0;
                    LD    <= 0;
                    ADD   <= 0;
                    count <= count + 1'b1;
                    state <= (count > HOLD_CYCLES) ? S_START : S_END;
                end

                default: state <= S_START;

            endcase
        end
    end


`ifdef BENCH
    reg [8*40:1] state_name;
    always @(*) begin
        case (state)
            S_START : state_name = "START";
            S_CHECK : state_name = "CHECK";
            S_ADD   : state_name = "ADD";
            S_SHIFT : state_name = "SHIFT";
            S_END   : state_name = "END";
        endcase
    end
`endif

endmodule

Multiplicador/Verilog/accumulator.v

// Module: accumulator
module accumulator #(
    parameter N = 16
)(
    input  wire         clk,
    input  wire         rst,
    input  wire         LD,
    input  wire         ADD,
    input  wire [N-1:0] X_in,
    output reg  [2*N-1:0] Q
);
    always @(negedge clk or posedge rst) begin
        if (rst)       Q <= {(2*N){1'b0}};
        else if (LD)   Q <= {(2*N){1'b0}};
        else if (ADD)  Q <= Q + X_in;
    end
endmodule

Multiplicador/Verilog/shift_register.v

// Module: shift_register
module shift_register #(
    parameter N   = 16,
    parameter DIR = 0
)(
    input  wire         clk,
    input  wire         rst,
    input  wire         LD,
    input  wire         SHIFT,
    input  wire [N-1:0] D,
    output reg  [N-1:0] Q,
    output wire         LSB
);
    assign LSB = Q[0];

    always @(negedge clk or posedge rst) begin
        if (rst)        Q <= {N{1'b0}};
        else if (LD)    Q <= D;
        else if (SHIFT) begin
            if (DIR == 1) Q <= {Q[N-2:0], 1'b0};   // X << 1
            else          Q <= {1'b0, Q[N-1:1]};    // Y >> 1
        end
    end
endmodule

Multiplicador/Verilog/multiplier.v
module multiplier #(parameter N = 16)(
    input  wire         clk, rst, start,
    input  wire [N-1:0] X_in, Y_in,
    output wire [2*N-1:0] P_out,
    output wire         done
);
    wire LD, SHIFT, ADD;
    wire Y_LSB, Y_ZERO;
    wire [N-1:0] X_shifted, Y_current;

    assign Y_ZERO = (Y_current == {N{1'b0}});

    shift_register #(.N(N),.DIR(1)) X_REG (.clk(clk),.rst(rst),.LD(LD),.SHIFT(SHIFT),.D(X_in),.Q(X_shifted),.LSB());
    shift_register #(.N(N),.DIR(0)) Y_REG (.clk(clk),.rst(rst),.LD(LD),.SHIFT(SHIFT),.D(Y_in),.Q(Y_current),.LSB(Y_LSB));
    accumulator    #(.N(N))         R_ACC (.clk(clk),.rst(rst),.LD(LD),.ADD(ADD),.X_in(X_shifted),.Q(P_out));
    control_unit                    FSM   (.clk(clk),.rst(rst),.start(start),.Y_LSB(Y_LSB),.Y_ZERO(Y_ZERO),.LD(LD),.SHIFT(SHIFT),.ADD(ADD),.DONE(done));
endmodule

Multiplicador/Verilog/tb_multiplier.v
`timescale 1ns/1ps
`include "multiplier.v"
`include "accumulator.v"
`include "shift_register.v"
`include "control_unit.v"

module tb_multiplier;

    parameter N = 16;

    reg clk;
    reg rst;
    reg start;

    reg  [N-1:0] X_in;
    reg  [N-1:0] Y_in;

    wire [2*N-1:0] P_out;
    wire done;


    multiplier #(N) DUT (
        .clk(clk),
        .rst(rst),
        .start(start),
        .X_in(X_in),
        .Y_in(Y_in),
        .P_out(P_out),
        .done(done)
    );

    always #5 clk = ~clk;

    initial begin

        $dumpfile("multiplier.vcd");
        $dumpvars(0, tb_multiplier);

        // Inicialización
        clk   = 0;
        rst   = 1;
        start = 0;

        X_in  = 0;
        Y_in  = 0;

        #20;
        rst = 0;

        #10;
        X_in = 16'd15;
        Y_in = 16'd7;

        start = 1;
        #10;
        start = 0;

        // Esperar a DONE
        wait(done);

        #20;

        
// PRUEBA 2

        rst = 1;
        #10;
        rst = 0;

        #10;
        X_in = 16'd63;
        Y_in = 16'd9;

        start = 1;
        #10;
        start = 0;

        wait(done);

        #30;

        $finish;
    end

endmodule

Multiplicador/Verilog/multiplier.vcd
$date
	Thu Jul 16 16:44:50 2026
$end
$version
	Icarus Verilog
$end
$timescale
	1ps
$end
$scope module tb_multiplier $end
$var wire 1 ! done $end
$var wire 32 " P_out [31:0] $end
$var parameter 32 # N $end
$var reg 16 $ X_in [15:0] $end
$var reg 16 % Y_in [15:0] $end
$var reg 1 & clk $end
$var reg 1 ' rst $end
$var reg 1 ( start $end
$scope module DUT $end
$var wire 16 ) X_in [15:0] $end
$var wire 16 * Y_in [15:0] $end
$var wire 1 & clk $end
$var wire 1 ' rst $end
$var wire 1 ( start $end
$var wire 1 ! done $end
$var wire 16 + Y_current [15:0] $end
$var wire 1 , Y_ZERO $end
$var wire 1 - Y_LSB $end
$var wire 16 . X_shifted [15:0] $end
$var wire 1 / SHIFT $end
$var wire 32 0 P_out [31:0] $end
$var wire 1 1 LD $end
$var wire 1 2 ADD $end
$var parameter 32 3 N $end
$scope module FSM $end
$var wire 1 , Y_ZERO $end
$var wire 1 & clk $end
$var wire 1 ' rst $end
$var wire 1 ( start $end
$var wire 1 - Y_LSB $end
$var parameter 5 4 HOLD_CYCLES $end
$var parameter 3 5 S_ADD $end
$var parameter 3 6 S_CHECK $end
$var parameter 3 7 S_END $end
$var parameter 3 8 S_SHIFT $end
$var parameter 3 9 S_START $end
$var reg 1 2 ADD $end
$var reg 1 ! DONE $end
$var reg 1 1 LD $end
$var reg 1 / SHIFT $end
$var reg 5 : count [4:0] $end
$var reg 3 ; state [2:0] $end
$var reg 320 < state_name [320:1] $end
$upscope $end
$scope module R_ACC $end
$var wire 1 2 ADD $end
$var wire 1 1 LD $end
$var wire 1 & clk $end
$var wire 1 ' rst $end
$var wire 16 = X_in [15:0] $end
$var parameter 32 > N $end
$var reg 32 ? Q [31:0] $end
$upscope $end
$scope module X_REG $end
$var wire 16 @ D [15:0] $end
$var wire 1 1 LD $end
$var wire 1 / SHIFT $end
$var wire 1 & clk $end
$var wire 1 ' rst $end
$var wire 1 A LSB $end
$var parameter 32 B DIR $end
$var parameter 32 C N $end
$var reg 16 D Q [15:0] $end
$upscope $end
$scope module Y_REG $end
$var wire 16 E D [15:0] $end
$var wire 1 1 LD $end
$var wire 1 / SHIFT $end
$var wire 1 & clk $end
$var wire 1 ' rst $end
$var wire 1 - LSB $end
$var parameter 32 F DIR $end
$var parameter 32 G N $end
$var reg 16 H Q [15:0] $end
$upscope $end
$upscope $end
$upscope $end
$enddefinitions $end
$comment Show the parameter values. $end
$dumpall
b10000 G
b0 F
b10000 C
b1 B
b10000 >
b0 9
b11 8
b100 7
b1 6
b10 5
b11100 4
b10000 3
b10000 #
$end
#0
$dumpvars
b0 H
b0 E
b0 D
0A
b0 @
b0 ?
b0 =
b101001101010100010000010101001001010100 <
b0 ;
b0 :
02
01
b0 0
0/
b0 .
0-
1,
b0 +
b0 *
b0 )
0(
1'
0&
b0 %
b0 $
b0 "
0!
$end
#5000
1&
#10000
0&
#15000
1&
#20000
0&
0'
#25000
11
1&
#30000
1-
1A
0,
b111 +
b111 H
b1111 .
b1111 =
b1111 D
0&
1(
b111 %
b111 *
b111 E
b1111 $
b1111 )
b1111 @
#35000
b100001101001000010001010100001101001011 <
b1 ;
1&
#40000
0&
0(
#45000
b10000010100010001000100 <
b10 ;
01
1&
#50000
0&
#55000
b101001101001000010010010100011001010100 <
b11 ;
12
1&
#60000
b1111 "
b1111 0
b1111 ?
0&
#65000
b100001101001000010001010100001101001011 <
b1 ;
02
1/
1&
#70000
0A
b11 +
b11 H
b11110 .
b11110 =
b11110 D
0&
#75000
b10000010100010001000100 <
b10 ;
0/
1&
#80000
0&
#85000
b101001101001000010010010100011001010100 <
b11 ;
12
1&
#90000
b101101 "
b101101 0
b101101 ?
0&
#95000
b100001101001000010001010100001101001011 <
b1 ;
02
1/
1&
#100000
b111100 .
b111100 =
b111100 D
b1 +
b1 H
0&
#105000
b10000010100010001000100 <
b10 ;
0/
1&
#110000
0&
#115000
b101001101001000010010010100011001010100 <
b11 ;
12
1&
#120000
b1101001 "
b1101001 0
b1101001 ?
0&
#125000
b100001101001000010001010100001101001011 <
b1 ;
02
1/
1&
#130000
0-
1,
b0 +
b0 H
b1111000 .
b1111000 =
b1111000 D
0&
#135000
b101001101001000010010010100011001010100 <
b11 ;
0/
1&
#140000
0&
#145000
b10001010100111001000100 <
b100 ;
1/
1&
#150000
b11110000 .
b11110000 =
b11110000 D
0&
#155000
b1 :
0/
1!
1&
#160000
0&
#165000
b10 :
1&
#170000
0&
#175000
b101001101010100010000010101001001010100 <
b0 ;
b0 .
b0 =
b0 D
b0 "
b0 0
b0 ?
1&
1'
#180000
0&
#185000
b0 :
11
0!
1&
0'
#190000
1A
1-
b1111 .
b1111 =
b1111 D
0,
b111 +
b111 H
0&
#195000
b100001101001000010001010100001101001011 <
b1 ;
1&
1(
b1001 %
b1001 *
b1001 E
b111111 $
b111111 )
b111111 @
#200000
b1001 +
b1001 H
b111111 .
b111111 =
b111111 D
0&
#205000
b10000010100010001000100 <
b10 ;
01
1&
0(
#210000
0&
#215000
b101001101001000010010010100011001010100 <
b11 ;
12
1&
#220000
b111111 "
b111111 0
b111111 ?
0&
#225000
b100001101001000010001010100001101001011 <
b1 ;
02
1/
1&
#230000
0A
0-
b1111110 .
b1111110 =
b1111110 D
b100 +
b100 H
0&
#235000
b101001101001000010010010100011001010100 <
b11 ;
0/
1&
#240000
0&
#245000
b100001101001000010001010100001101001011 <
b1 ;
1/
1&
#250000
b11111100 .
b11111100 =
b11111100 D
b10 +
b10 H
0&
#255000
b101001101001000010010010100011001010100 <
b11 ;
0/
1&
#260000
0&
#265000
b100001101001000010001010100001101001011 <
b1 ;
1/
1&
#270000
1-
b111111000 .
b111111000 =
b111111000 D
b1 +
b1 H
0&
#275000
b10000010100010001000100 <
b10 ;
0/
1&
#280000
0&
#285000
b101001101001000010010010100011001010100 <
b11 ;
12
1&
#290000
b1000110111 "
b1000110111 0
b1000110111 ?
0&
#295000
b100001101001000010001010100001101001011 <
b1 ;
02
1/
1&
#300000
0-
1,
b0 +
b0 H
b1111110000 .
b1111110000 =
b1111110000 D
0&
#305000
b101001101001000010010010100011001010100 <
b11 ;
0/
1&
#310000
0&
#315000
b10001010100111001000100 <
b100 ;
1/
1&
#320000
b11111100000 .
b11111100000 =
b11111100000 D
0&
#325000
b1 :
0/
1!
1&
#330000
0&
#335000
b10 :
1&
#340000
0&
#345000
b11 :
1&
#350000
0&
#355000
b100 :
1&
